{
    "__comment": "Model generated using MrCrayfish's Model Creator (http://mrcrayfish.com/modelcreator/)",
"ambientocclusion": false,
    "textures": {
        "particle": "blocks/blocks/angelicstatue",
        "0": "blocks/angelicstatue"
    },
    "elements": [
        {
            "name": "Body1",
            "from": [ 0.0, 0.0, 0.0 ], 
            "to": [ 16.0, 6.0, 16.0 ], 
            "faces": {
                "north": { "texture": "#0", "uv": [ 6.0, 2.0, 8.0, 2.75 ] },
                "east": { "texture": "#0", "uv": [ 4.0, 2.0, 6.0, 2.75 ] },
                "south": { "texture": "#0", "uv": [ 2.0, 2.0, 4.0, 2.75 ] },
                "west": { "texture": "#0", "uv": [ 0.0, 2.0, 2.0, 2.75 ] },
                "up": { "texture": "#0", "uv": [ 1.5, 0.0, 4.5, 2.0 ] },
                "down": { "texture": "#0", "uv": [ 3.0, 0.0, 6.0, 2.0 ] }
            }
        },
        {
            "name": "Body2",
            "from": [ 2.0, 6.0, 2.0 ], 
            "to": [ 14.0, 10.0, 14.0 ], 
            "faces": {
                "north": { "texture": "#0", "uv": [ 4.5, 1.5, 6.0, 2.0 ] },
                "east": { "texture": "#0", "uv": [ 3.0, 1.5, 4.5, 2.0 ] },
                "south": { "texture": "#0", "uv": [ 1.5, 1.5, 3.0, 2.0 ] },
                "west": { "texture": "#0", "uv": [ 0.0, 1.5, 1.5, 2.0 ] },
                "up": { "texture": "#0", "uv": [ 1.5, 0.0, 3.0, 1.5 ] },
                "down": { "texture": "#0", "uv": [ 0.0, 0.0, 1.0, 2.0 ] }
            }
        },
        {
            "name": "Body3",
            "from": [ 4.0, 10.0, 4.0 ], 
            "to": [ 12.0, 14.0, 12.0 ], 
            "faces": {
                "north": { "texture": "#0", "uv": [ 6.0, 2.0, 8.0, 2.75 ] },
                "east": { "texture": "#0", "uv": [ 4.0, 2.0, 6.0, 2.75 ] },
                "south": { "texture": "#0", "uv": [ 2.0, 2.0, 4.0, 2.75 ] },
                "west": { "texture": "#0", "uv": [ 0.0, 3.75, 1.0, 4.25 ] },
                "up": { "texture": "#0", "uv": [ 1.0, 2.75, 2.0, 3.75 ] },
                "down": { "texture": "#0", "uv": [ 0.0, 22.0, 128.0, 128.0 ] }
            }
        },
        {
            "name": "Body4",
            "from": [ 6.0, 14.0, 6.0 ], 
            "to": [ 10.0, 18.0, 10.0 ], 
            "faces": {
                "north": { "texture": "#0", "uv": [ 1.5, 0.5, 2.0, 1.0 ] },
                "east": { "texture": "#0", "uv": [ 1.0, 0.5, 1.5, 1.0 ] },
                "south": { "texture": "#0", "uv": [ 0.5, 0.5, 1.0, 1.0 ] },
                "west": { "texture": "#0", "uv": [ 0.0, 0.5, 0.5, 1.0 ] },
                "up": { "texture": "#0", "uv": [ 0.5, 0.0, 1.0, 0.5 ] },
                "down": { "texture": "#0", "uv": [ 0.0, 0.0, 6.0, 6.0 ] }
            }
        },
        {
            "name": "Base_1_1",
            "from": [ 9.0, 17.0, 7.0 ], 
            "to": [ 19.0, 18.0, 9.0 ], 
            "rotation": { "origin": [ 10.0, 18.0, 8.0 ], "axis": "z", "angle": 22.5 },
            "faces": {
                "north": { "texture": "#0", "uv": [ 7.5, 7.625, 8.75, 7.75 ] },
                "east": { "texture": "#0", "uv": [ 8.75, 7.625, 9.0, 7.75 ] },
                "south": { "texture": "#0", "uv": [ 9.0, 7.625, 10.25, 7.75 ] },
                "west": { "texture": "#0", "uv": [ 8.75, 7.625, 9.0, 7.75 ] },
                "up": { "texture": "#0", "uv": [ 7.5, 7.375, 8.75, 7.625 ] },
                "down": { "texture": "#0", "uv": [ 8.75, 7.375, 10.0, 7.625 ] }
            }
        },
        {
            "name": "Base_1_2",
            "from": [ 18.2, 20.4, 7.0 ], 
            "to": [ 28.2, 21.4, 9.0 ], 
            "faces": {
                "north": { "texture": "#0", "uv": [ 7.5, 7.25, 8.75, 7.375 ] },
                "east": { "texture": "#0", "uv": [ 8.75, 7.25, 9.0, 7.375 ] },
                "south": { "texture": "#0", "uv": [ 9.0, 7.25, 10.25, 7.375 ] },
                "west": { "texture": "#0", "uv": [ 7.25, 7.25, 7.5, 7.375 ] },
                "up": { "texture": "#0", "uv": [ 7.5, 7.0, 8.75, 7.25 ] },
                "down": { "texture": "#0", "uv": [ 8.75, 7.0, 10.0, 7.25 ] }
            }
        },
        {
            "name": "Base_1_3",
            "from": [ 28.0, 20.5, 7.0 ], 
            "to": [ 36.0, 21.5, 9.0 ], 
            "rotation": { "origin": [ 28.0, 21.0, 8.0 ], "axis": "z", "angle": -45.0 },
            "faces": {
                "north": { "texture": "#0", "uv": [ 7.5, 6.875, 8.5, 7.0 ] },
                "east": { "texture": "#0", "uv": [ 8.5, 6.875, 8.75, 7.0 ] },
                "south": { "texture": "#0", "uv": [ 8.75, 6.875, 9.75, 7.0 ] },
                "west": { "texture": "#0", "uv": [ 7.25, 6.875, 7.5, 7.0 ] },
                "up": { "texture": "#0", "uv": [ 7.5, 6.625, 8.5, 6.875 ] },
                "down": { "texture": "#0", "uv": [ 8.5, 6.625, 9.5, 6.875 ] }
            }
        },
        {
            "name": "Base_2_1",
            "from": [ -3.0, 17.0, 7.0 ], 
            "to": [ 7.0, 18.0, 9.0 ], 
            "faces": {
                "north": { "texture": "#0", "uv": [ 6.0, 7.625, 7.25, 7.75 ] },
                "east": { "texture": "#0", "uv": [ 4.25, 7.625, 4.5, 7.75 ] },
                "south": { "texture": "#0", "uv": [ 4.5, 7.625, 5.75, 7.75 ] },
                "west": { "texture": "#0", "uv": [ 5.75, 7.625, 6.0, 7.75 ] },
                "up": { "texture": "#0", "uv": [ 4.5, 7.375, 5.75, 7.625 ] },
                "down": { "texture": "#0", "uv": [ 5.75, 7.375, 7.0, 7.625 ] }
            }
        },
        {
            "name": "Base_2_2",
            "from": [ -11.9, 20.9, 7.0 ], 
            "to": [ -1.9000000000000004, 21.9, 9.0 ], 
            "faces": {
                "north": { "texture": "#0", "uv": [ 6.0, 7.25, 7.25, 7.375 ] },
                "east": { "texture": "#0", "uv": [ 4.25, 7.25, 4.5, 7.375 ] },
                "south": { "texture": "#0", "uv": [ 4.5, 7.25, 5.75, 7.375 ] },
                "west": { "texture": "#0", "uv": [ 5.75, 7.25, 6.0, 7.375 ] },
                "up": { "texture": "#0", "uv": [ 4.5, 7.375, 5.75, 7.625 ] },
                "down": { "texture": "#0", "uv": [ 5.75, 7.0, 7.0, 7.25 ] }
            }
        },
        {
            "name": "Base_2_3",
            "from": [ -18.4, 17.0, 7.0 ], 
            "to": [ -10.4, 18.0, 9.0 ], 
            "faces": {
                "north": { "texture": "#0", "uv": [ 5.75, 6.875, 6.75, 7.0 ] },
                "east": { "texture": "#0", "uv": [ 4.25, 6.875, 4.5, 7.0 ] },
                "south": { "texture": "#0", "uv": [ 4.5, 6.875, 5.5, 7.0 ] },
                "west": { "texture": "#0", "uv": [ 5.5, 6.875, 5.75, 7.0 ] },
                "up": { "texture": "#0", "uv": [ 4.5, 6.625, 5.5, 6.875 ] },
                "down": { "texture": "#0", "uv": [ 5.5, 6.625, 6.5, 6.875 ] }
            }
        },
        {
            "name": "Wing_2",
            "from": [ -18.0, 6.0, 7.0 ], 
            "to": [ 4.0, 21.0, 9.0 ], 
            "faces": {
                "north": { "texture": "#0", "uv": [ 2.25, 6.625, 4.25, 8.0 ] },
                "east": { "texture": "#0", "uv": [ 2.125, 6.625, 2.25, 8.0 ] },
                "south": { "texture": "#0", "uv": [ 0.125, 6.625, 2.125, 8.0 ] },
                "west": { "texture": "#0", "uv": [ 0.0, 6.625, 0.125, 8.0 ] },
                "up": { "texture": "#0", "uv": [ 0.125, 6.5, 2.125, 6.625 ] },
                "down": { "texture": "#0", "uv": [ 2.125, 6.5, 4.125, 6.625 ] }
            }
        },
        {
            "name": "Wing_1",
            "from": [ 9.0, 12.0, 7.0 ], 
            "to": [ 31.0, 27.0, 9.0 ], 
            "faces": {
                "north": { "texture": "#0", "uv": [ 6.5, 8.125, 8.5, 9.5 ] },
                "east": { "texture": "#0", "uv": [ 6.375, 8.125, 6.5, 9.5 ] },
                "south": { "texture": "#0", "uv": [ 4.375, 8.125, 6.375, 9.5 ] },
                "west": { "texture": "#0", "uv": [ 4.25, 8.125, 4.375, 9.5 ] },
                "up": { "texture": "#0", "uv": [ 4.375, 8.0, 6.375, 8.125 ] },
                "down": { "texture": "#0", "uv": [ 6.375, 8.0, 8.375, 8.125 ] }
            }
        }
    ]
}